{"$schema":"https://json-schema.org/draft/2020-12/schema","$id":"urn:att:schema:ci-summary:v2.1","type":"object","required":["schemaVersion","attVersion","runId","environment","startedAt","endedAt","status","summary","durationStatistics","cases","diagnosticCounts","report","inputManifestHash"],"properties":{"schemaVersion":{"const":"att-ci-summary/v2.1"},"attVersion":{"type":"string"},"runId":{"type":"string"},"environment":{"type":"string"},"startedAt":{"type":"string"},"endedAt":{"type":"string"},"status":{"type":"string"},"summary":{"type":"object"},"durationStatistics":{"type":"object"},"cases":{"type":"array"},"diagnosticCounts":{"type":"object"},"report":{"type":"string"},"inputManifestHash":{"type":"string"}},"additionalProperties":false}
